MANIFEST.in
README.txt
VERSION.txt
setup.cfg
setup.py
docs/Makefile
docs/source/News.rst
docs/source/conf.py
docs/source/index.rst
docs/source/_static/logo_hi.gif
docs/source/_static/repoze.css
repoze/__init__.py
repoze.who_friendlyform.egg-info/PKG-INFO
repoze.who_friendlyform.egg-info/SOURCES.txt
repoze.who_friendlyform.egg-info/dependency_links.txt
repoze.who_friendlyform.egg-info/entry_points.txt
repoze.who_friendlyform.egg-info/namespace_packages.txt
repoze.who_friendlyform.egg-info/not-zip-safe
repoze.who_friendlyform.egg-info/requires.txt
repoze.who_friendlyform.egg-info/top_level.txt
repoze/who/__init__.py
repoze/who/plugins/__init__.py
repoze/who/plugins/friendlyform.py