Metadata-Version: 1.0
Name: repoze.who-friendlyform
Version: 1.0.3
Summary: Collection of repoze.who friendly form plugins
Home-page: http://code.gustavonarea.net/repoze.who-friendlyform/
Author: Gustavo Narea
Author-email: repoze-dev@lists.repoze.org
License: BSD-derived (http://www.repoze.org/LICENSE.txt)
Keywords: web application wsgi server authentication forms repoze
Platform: UNKNOWN
Classifier: Development Status :: 5 - Production/Stable
Classifier: Environment :: Web Environment
Classifier: Intended Audience :: Developers
Classifier: Natural Language :: English
Classifier: Operating System :: OS Independent
Classifier: Programming Language :: Python
Classifier: Topic :: Internet :: WWW/HTTP :: WSGI
Classifier: Topic :: Security
